mobio/libs/caching/__init__.py
m_caching-0.1.8.dist-info/METADATA
m_caching-0.1.8.dist-info/WHEEL
m_caching-0.1.8.dist-info/top_level.txt
m_caching-0.1.8.dist-info/RECORD
