Metadata-Version: 2.1
Name: m-caching
Version: 0.1.8
Summary: Setup normal class to mobio lru cache
Home-page: https://github.com/mobiovn
Author: MOBIO
Author-email: contact@mobio.vn
License: MIT
Platform: UNKNOWN
Requires-Dist: redis
